LICENSE
MANIFEST.in
README.md
dev_requirements.txt
requirements.txt
setup.py
pymetric/__init__.py
pymetric/extras.py
pymetric/metrics.py
pymetric.egg-info/PKG-INFO
pymetric.egg-info/SOURCES.txt
pymetric.egg-info/dependency_links.txt
pymetric.egg-info/requires.txt
pymetric.egg-info/top_level.txt